README.md
setup.py
KafNafParserPy/KafNafParserMod.py
KafNafParserPy/__init__.py
KafNafParserPy/attribution_data.py
KafNafParserPy/causal_data.py
KafNafParserPy/chunk_data.py
KafNafParserPy/constituency_data.py
KafNafParserPy/coreference_data.py
KafNafParserPy/dependency_data.py
KafNafParserPy/entity_data.py
KafNafParserPy/external_references_data.py
KafNafParserPy/factuality_data.py
KafNafParserPy/features_data.py
KafNafParserPy/header_data.py
KafNafParserPy/markable_data.py
KafNafParserPy/opinion_data.py
KafNafParserPy/references_data.py
KafNafParserPy/span_data.py
KafNafParserPy/srl_data.py
KafNafParserPy/temporal_data.py
KafNafParserPy/term_data.py
KafNafParserPy/term_sentiment_data.py
KafNafParserPy/text_data.py
KafNafParserPy/time_data.py
KafNafParserPy.egg-info/PKG-INFO
KafNafParserPy.egg-info/SOURCES.txt
KafNafParserPy.egg-info/dependency_links.txt
KafNafParserPy.egg-info/requires.txt
KafNafParserPy.egg-info/top_level.txt
KafNafParserPy/feature_extractor/__init__.py
KafNafParserPy/feature_extractor/constituency.py
KafNafParserPy/feature_extractor/dependency.py