Metadata-Version: 1.0
Name: KafNafParserPy
Version: 1.896
Summary: Parser for KAF/NAF files in Python
Home-page: https://github.com/cltl/KafNafParserPy
Author: Ruben Izquierdo
Author-email: rubensanvi@gmail.com
License: UNKNOWN
Platform: UNKNOWN
